taskbrain/__init__.py
taskbrain/brain.py
taskbrain/dict_proxy.py
taskbrain/execution_states.py
taskbrain/task.py
taskbrain/task_output.py
taskbrain/task_wrappers.py
taskbrain-0.1.8.dist-info/LICENSE
taskbrain-0.1.8.dist-info/METADATA
taskbrain-0.1.8.dist-info/WHEEL
taskbrain-0.1.8.dist-info/top_level.txt
taskbrain-0.1.8.dist-info/RECORD
