Metadata-Version: 2.2
Name: taskbrain
Version: 0.1.8
Summary: A simple and powerful task scheduler.
Home-page: https://github.com/Florian-BARRE/TaskBrain
Author: Florian BARRE
Author-email: florian.barre78@gmail.com
Classifier: Programming Language :: Python :: 3
Classifier: License :: OSI Approved :: GNU General Public License v2 (GPLv2)
Classifier: Operating System :: OS Independent
Requires-Python: >=3.10
License-File: LICENSE
Requires-Dist: colorama>=0.4.6
Requires-Dist: contourpy>=1.3.1
Requires-Dist: cycler>=0.12.1
Requires-Dist: fonttools>=4.55.8
Requires-Dist: kiwisolver>=1.4.8
Requires-Dist: matplotlib>=3.10.0
Requires-Dist: numpy>=2.2.2
Requires-Dist: packaging>=24.2
Requires-Dist: pillow>=11.1.0
Requires-Dist: pyparsing>=3.2.1
Requires-Dist: python-dateutil>=2.9.0.post0
Requires-Dist: six>=1.17.0
Requires-Dist: loggerplusplus>=0.1.2
Dynamic: author
Dynamic: author-email
Dynamic: classifier
Dynamic: description
Dynamic: description-content-type
Dynamic: home-page
Dynamic: requires-dist
Dynamic: requires-python
Dynamic: summary
